atlas/Snakefile
atlas/__init__.py
atlas/atlas.py
atlas/blast.py
atlas/conf.py
atlas/default_values.py
atlas/parsers.py
atlas/tables.py
atlas/template_config.yaml
atlas/utils.py
atlas/workflows.py
atlas/envs/optional_genome_binning.yaml
atlas/envs/report.yaml
atlas/envs/required_packages.yaml
atlas/report/assembly_report.py
atlas/report/bin_report.py
atlas/report/qc_report.py
atlas/report/report.css
atlas/rules/annotate.snakefile
atlas/rules/assemble.snakefile
atlas/rules/download.snakefile
atlas/rules/initialize_checkm.py
atlas/rules/qc.snakefile
pnnl_atlas-1.0.32.dist-info/DESCRIPTION.rst
pnnl_atlas-1.0.32.dist-info/METADATA
pnnl_atlas-1.0.32.dist-info/RECORD
pnnl_atlas-1.0.32.dist-info/WHEEL
pnnl_atlas-1.0.32.dist-info/entry_points.txt
pnnl_atlas-1.0.32.dist-info/metadata.json
pnnl_atlas-1.0.32.dist-info/top_level.txt
