Metadata-Version: 2.0
Name: pnnl-atlas
Version: 1.0.32
Summary: ATLAS - a framework for assembly, annotation, and genomic binning of metagenomic and metatranscriptomic data
Home-page: https://github.com/pnnl/atlas
Author: Joe Brown
Author-email: joe.brown@pnnl.gov
License: MIT
Platform: UNKNOWN
Classifier: Topic :: Scientific/Engineering :: Bio-Informatics
Requires-Dist: ruamel.yaml (==0.15.35)
